setup.py
gaubidistributions/Binomialdistribution.py
gaubidistributions/Gaussiandistribution.py
gaubidistributions/Generaldistribution.py
gaubidistributions/__init__.py
gaubidistributions.egg-info/PKG-INFO
gaubidistributions.egg-info/SOURCES.txt
gaubidistributions.egg-info/dependency_links.txt
gaubidistributions.egg-info/not-zip-safe
gaubidistributions.egg-info/top_level.txt